LICENSE
MANIFEST.in
README.md
setup.py
django_admin_terminal/__init__.py
django_admin_terminal/admin.py
django_admin_terminal/tests.py
django_admin_terminal.egg-info/PKG-INFO
django_admin_terminal.egg-info/SOURCES.txt
django_admin_terminal.egg-info/dependency_links.txt
django_admin_terminal.egg-info/not-zip-safe
django_admin_terminal.egg-info/top_level.txt
django_admin_terminal/static/readme.txt
django_admin_terminal/static/images/console-128x128.png
django_admin_terminal/static/images/console.png
django_admin_terminal/static/images/screenshot.png
django_admin_terminal/static/js/termlib.js
django_admin_terminal/templates/django_admin_terminal/admin/index.html
venv/bin/rst2html.py
venv/bin/rst2html4.py
venv/bin/rst2html5.py
venv/bin/rst2latex.py
venv/bin/rst2man.py
venv/bin/rst2odt.py
venv/bin/rst2odt_prepstyles.py
venv/bin/rst2pseudoxml.py
venv/bin/rst2s5.py
venv/bin/rst2xetex.py
venv/bin/rst2xml.py
venv/bin/rstpep2html.py
venv/lib/python3.9/site-packages/easy_install.py
venv/lib/python3.9/site-packages/pyparsing.py
venv/lib/python3.9/site-packages/six.py
venv/lib/python3.9/site-packages/Pygments-2.7.3.dist-info/entry_points.txt
venv/lib/python3.9/site-packages/Pygments-2.7.3.dist-info/top_level.txt
venv/lib/python3.9/site-packages/_distutils_hack/__init__.py
venv/lib/python3.9/site-packages/_distutils_hack/override.py
venv/lib/python3.9/site-packages/bleach/__init__.py
venv/lib/python3.9/site-packages/bleach/callbacks.py
venv/lib/python3.9/site-packages/bleach/html5lib_shim.py
venv/lib/python3.9/site-packages/bleach/linkifier.py
venv/lib/python3.9/site-packages/bleach/sanitizer.py
venv/lib/python3.9/site-packages/bleach/utils.py
venv/lib/python3.9/site-packages/bleach-3.2.1.dist-info/top_level.txt
venv/lib/python3.9/site-packages/bleach/_vendor/__init__.py
venv/lib/python3.9/site-packages/bleach/_vendor/vendor.txt
venv/lib/python3.9/site-packages/bleach/_vendor/html5lib/__init__.py
venv/lib/python3.9/site-packages/bleach/_vendor/html5lib/_ihatexml.py
venv/lib/python3.9/site-packages/bleach/_vendor/html5lib/_inputstream.py
venv/lib/python3.9/site-packages/bleach/_vendor/html5lib/_tokenizer.py
venv/lib/python3.9/site-packages/bleach/_vendor/html5lib/_utils.py
venv/lib/python3.9/site-packages/bleach/_vendor/html5lib/constants.py
venv/lib/python3.9/site-packages/bleach/_vendor/html5lib/html5parser.py
venv/lib/python3.9/site-packages/bleach/_vendor/html5lib/serializer.py
venv/lib/python3.9/site-packages/bleach/_vendor/html5lib-1.1.dist-info/top_level.txt
venv/lib/python3.9/site-packages/certifi-2020.12.5.dist-info/top_level.txt
venv/lib/python3.9/site-packages/chardet-4.0.0.dist-info/entry_points.txt
venv/lib/python3.9/site-packages/chardet-4.0.0.dist-info/top_level.txt
venv/lib/python3.9/site-packages/colorama-0.4.4.dist-info/LICENSE.txt
venv/lib/python3.9/site-packages/colorama-0.4.4.dist-info/top_level.txt
venv/lib/python3.9/site-packages/docutils-0.16.dist-info/COPYING.txt
venv/lib/python3.9/site-packages/docutils-0.16.dist-info/top_level.txt
venv/lib/python3.9/site-packages/idna-2.10.dist-info/top_level.txt
venv/lib/python3.9/site-packages/keyring-21.5.0.dist-info/entry_points.txt
venv/lib/python3.9/site-packages/keyring-21.5.0.dist-info/top_level.txt
venv/lib/python3.9/site-packages/packaging-20.8.dist-info/top_level.txt
venv/lib/python3.9/site-packages/pip-20.3.3.dist-info/LICENSE.txt
venv/lib/python3.9/site-packages/pip-20.3.3.dist-info/entry_points.txt
venv/lib/python3.9/site-packages/pip-20.3.3.dist-info/top_level.txt
venv/lib/python3.9/site-packages/pkginfo-1.6.1.dist-info/LICENSE.txt
venv/lib/python3.9/site-packages/pkginfo-1.6.1.dist-info/entry_points.txt
venv/lib/python3.9/site-packages/pkginfo-1.6.1.dist-info/top_level.txt
venv/lib/python3.9/site-packages/pyparsing-2.4.7.dist-info/top_level.txt
venv/lib/python3.9/site-packages/readme_renderer-28.0.dist-info/entry_points.txt
venv/lib/python3.9/site-packages/readme_renderer-28.0.dist-info/top_level.txt
venv/lib/python3.9/site-packages/requests-2.25.1.dist-info/top_level.txt
venv/lib/python3.9/site-packages/requests_toolbelt-0.9.1.dist-info/top_level.txt
venv/lib/python3.9/site-packages/rfc3986-1.4.0.dist-info/top_level.txt
venv/lib/python3.9/site-packages/setuptools-51.0.0.dist-info/dependency_links.txt
venv/lib/python3.9/site-packages/setuptools-51.0.0.dist-info/entry_points.txt
venv/lib/python3.9/site-packages/setuptools-51.0.0.dist-info/top_level.txt
venv/lib/python3.9/site-packages/six-1.15.0.dist-info/top_level.txt
venv/lib/python3.9/site-packages/tqdm-4.54.1.dist-info/entry_points.txt
venv/lib/python3.9/site-packages/tqdm-4.54.1.dist-info/top_level.txt
venv/lib/python3.9/site-packages/twine-3.2.0.dist-info/entry_points.txt
venv/lib/python3.9/site-packages/twine-3.2.0.dist-info/top_level.txt
venv/lib/python3.9/site-packages/urllib3-1.26.2.dist-info/LICENSE.txt
venv/lib/python3.9/site-packages/urllib3-1.26.2.dist-info/top_level.txt
venv/lib/python3.9/site-packages/webencodings-0.5.1.dist-info/top_level.txt
venv/lib/python3.9/site-packages/wheel-0.36.2.dist-info/LICENSE.txt
venv/lib/python3.9/site-packages/wheel-0.36.2.dist-info/entry_points.txt
venv/lib/python3.9/site-packages/wheel-0.36.2.dist-info/top_level.txt
