Metadata-Version: 1.1
Name: django-admin-terminal
Version: 0.5.1
Summary: bash console in the browser for django admins
Home-page: http://github.com/assem-ch/django-admin-terminal
Author: Assem Chelli
Author-email: assem.ch@gmail.com
License: BSD License
Keywords: django,bash,terminal,console,server
Platform: all
Classifier: Development Status :: 4 - Beta
Classifier: Environment :: Web Environment
Classifier: Framework :: Django
Classifier: Intended Audience :: Developers
Classifier: License :: OSI Approved :: GNU General Public License (GPL)
Classifier: Operating System :: OS Independent
Classifier: Programming Language :: Python
Classifier: Topic :: Internet :: WWW/HTTP
Classifier: Topic :: Software Development :: Libraries :: Application Frameworks
Classifier: Topic :: Software Development :: Libraries :: Python Modules
